boxobj/__init__.py
boxobj-0.1.2.dist-info/METADATA
boxobj-0.1.2.dist-info/WHEEL
boxobj-0.1.2.dist-info/RECORD
