Metadata-Version: 2.1
Name: boxobj
Version: 0.1.2
Summary: A simple library to making working with regions of an image (OCR, CV, etc) easier to work with
License: MIT
Author: dschultz0
Author-email: dave@daveschultzconsulting.com
Requires-Python: >=3.8,<4.0
Classifier: License :: OSI Approved :: MIT License
Classifier: Programming Language :: Python :: 3
Classifier: Programming Language :: Python :: 3.8
Classifier: Programming Language :: Python :: 3.9
Classifier: Programming Language :: Python :: 3.10
Classifier: Programming Language :: Python :: 3.11
Classifier: Programming Language :: Python :: 3.12
